simple_sock/__init__.py
simple_sock/sock.py
simple_sock-0.1.4.dist-info/LICENSE
simple_sock-0.1.4.dist-info/METADATA
simple_sock-0.1.4.dist-info/WHEEL
simple_sock-0.1.4.dist-info/top_level.txt
simple_sock-0.1.4.dist-info/RECORD
