Metadata-Version: 2.1
Name: simple_sock
Version: 0.1.4
Summary: A Python library for simplified network and HTTP connections management.
Author: Leonardo Oliveira
Author-email: lo570354@gmail.com
Keywords: simplified,socket,simple,sock,network,easy
Classifier: Programming Language :: Python :: 3
Classifier: License :: OSI Approved :: MIT License
Classifier: Operating System :: OS Independent
Classifier: Intended Audience :: Developers
Classifier: Topic :: Software Development :: Libraries :: Python Modules
Requires-Python: >=3.6
License-File: LICENSE
